dwaoHelloWorld/__init.py
dwaoHelloWorld/helloWorld.py
dwaoHelloWorld-0.0.1.dist-info/METADATA
dwaoHelloWorld-0.0.1.dist-info/WHEEL
dwaoHelloWorld-0.0.1.dist-info/top_level.txt
dwaoHelloWorld-0.0.1.dist-info/RECORD
