Metadata-Version: 2.1
Name: dwaoHelloWorld
Version: 0.0.1
Summary: DWAO Hello World Project
Home-page: UNKNOWN
Author: Ketav Sharma
Author-email: ketavsharma@dwao.in
License: UNKNOWN
Platform: UNKNOWN
Classifier: Programming Language :: Python :: 3
Classifier: License :: OSI Approved :: MIT License
Classifier: Operating System :: OS Independent
Requires-Dist: requests
